[
    {
        "id": 1,
        "_id": 1,
        "route_title": "199 автобус",
        "stop_title": "Аэродромная 18",
        "times": [
            {
                "to": "Химки",
                "times": ["13:40", "14:10", "14:50", "15:30"]
            }
        ]
    },
    {
        "id": 2,
        "_id": 2,
        "route_title": "199 автобус",
        "stop_title": "Аэродромная 18",
        "times": [
            {
                "to": "Химки",
                "times": ["13:40", "14:10", "14:50", "15:30"]
            }
        ]
    }
]